7400/SN74LS173/SN74LS173.v
module SN74LS173(D, Q, CLK, CLR, G_bar, M, N);
   input [4:1] D;
   output reg [4:1] Q;
   input [2:1] G_bar;
   input CLK, CLR, M, N;

   reg [4:1] Q_store;

   assign Q = (M | N) ? 4'hz : Q_store;

   always @(posedge CLK, CLR) begin
      if (CLR)
        Q_store <= 0;
      else
        if (!G_bar[1] && !G_bar[2])
          Q_store <= D;
   end
endmodule

module SN74LS173_tb;
   reg [4:1] d;
   reg CLK;
   reg CLR;
   wire [4:1] q;
   reg m, n;
   reg [2:1] g_bar;
   SN74LS173 DUT(.D(d), .Q(q), .CLK(CLK), .CLR(CLR), .G_bar(g_bar), .M(m), .N(n));

   initial begin
      // Waveform generation
      $dumpfile("SN74LS173_tb.vcd");
      $dumpvars(0, SN74LS173_tb);
      $display("------------------");
      $display("Set Output to Q");
      m = 0;
      n = 0;
      $display("Enable Data Writing");
      g_bar = 2'b00;
      d = 4'h9;
      $display("Set Data to %h", d);
      CLK=0;
      $display("Enable Clear");
      CLR = 1;
      forever #1 CLK = ~CLK;
   end
   initial begin
      #1
      $display("Disable Clear");
      CLR = 0;
      #1;
      d = 4'h3;
      $display("Set Data to %h", d);
      #1
      $display("Set Output to High Impedence");
      m = 1;
      n = 1;
      #1;
      d = 4'hC;
      $display("Set Data to %h", d);
      #1
      $display("Set Output to Q");
      m = 0;
      n = 0;
      #1;
      $display("Disable Data Writing");
      g_bar = 2'b11;
      #1;
      d = 4'hF;
      $display("Set Data to %h", d);
      #1
      $display("------------------");
      $finish;
   end
endmodule

SAP-1/Architecture/Instruction Register/Instruction_Register.v
`include "../../../7400/SN74LS173/SN74LS173.v"
module Instruction_Register(L_I_bar, CLK, CLR, E_I_bar, bus_input, data, instruction);
   input  L_I_bar;
   input  CLK;
   input  CLR;
   input  E_I_bar;
   input [7:0] bus_input;
   output [3:0] data;
   output [3:0] instruction;

   wire [3:0] bus_input_first_nibble;
   wire [3:0] bus_input_second_nibble;
   assign {bus_input_second_nibble, bus_input_first_nibble} = bus_input;

   wire gnd = 0;

   SN74LS173 register_1(.D(bus_input_first_nibble), .Q(data), .CLK(CLK), .CLR(gnd), .G_bar({2{L_I_bar}}), .M(E_I_bar), .N(E_I_bar));
   SN74LS173 register_2(.D(bus_input_second_nibble), .Q(instruction), .CLK(CLK), .CLR(CLR), .G_bar({2{L_I_bar}}), .M(gnd), .N(gnd));
endmodule

module Instruction_Register_tb;
   `ifdef Instruction_Register_test
   reg L_I_bar;
   reg CLK;
   reg CLR;
   reg E_I_bar;
   reg [7:0] bus_input;
   wire [3:0] data;
   wire [3:0] instruction;

   Instruction_Register DUT(L_I_bar, CLK, CLR, E_I_bar, bus_input, data, instruction);

   initial begin
      // Waveform generation
      $dumpfile("Instruction_Register_tb.vcd");
      $dumpvars(0, Instruction_Register_tb);
      // Disable loading data into the Instruction register
      L_I_bar = 1;
      // Disable data output
      E_I_bar = 1;
      // Set bus value
      bus_input = 8'hAC;
      CLK = 0;
      forever #1 CLK = ~CLK;
   end
   initial begin
      // Clear the register
      CLR = 0; #1;
      CLR = 1; #1;
      CLR = 0; #1;
      // Enable loading data into the Instruction register
      L_I_bar = 0; #2;
      // Enable data output
      E_I_bar = 0; #2;
      // Set bus value
      bus_input = 8'h3D; #2;
      // Diable loading data into the Instruction register
      L_I_bar = 1; #2;
      // Set bus value
      bus_input = 8'hff; #2;
      // Disable data output
      E_I_bar = 1; #2;
      // Clear the register
      CLR = 0; #1;
      CLR = 1; #1;
      CLR = 0; #1;
      #5;

      $finish;
   end
   `endif
endmodule

SAP-1/Architecture/Instruction Register/Instruction_Register_tb.vcd
$date
	Sat Dec  9 11:14:13 2023
$end
$version
	Icarus Verilog
$end
$timescale
	1s
$end
$scope module Instruction_Register_tb $end
$var wire 4 ! instruction [3:0] $end
$var wire 4 " data [3:0] $end
$var reg 1 # CLK $end
$var reg 1 $ CLR $end
$var reg 1 % E_I_bar $end
$var reg 1 & L_I_bar $end
$var reg 8 ' bus_input [7:0] $end
$scope module DUT $end
$var wire 1 # CLK $end
$var wire 1 $ CLR $end
$var wire 1 % E_I_bar $end
$var wire 1 & L_I_bar $end
$var wire 8 ( bus_input [7:0] $end
$var wire 1 ) gnd $end
$var wire 4 * instruction [3:0] $end
$var wire 4 + data [3:0] $end
$var wire 4 , bus_input_second_nibble [3:0] $end
$var wire 4 - bus_input_first_nibble [3:0] $end
$scope module register_1 $end
$var wire 1 # CLK $end
$var wire 1 ) CLR $end
$var wire 4 . D [4:1] $end
$var wire 2 / G_bar [2:1] $end
$var wire 1 % M $end
$var wire 1 % N $end
$var wire 4 0 Q [4:1] $end
$var reg 4 1 Q_store [4:1] $end
$upscope $end
$scope module register_2 $end
$var wire 1 # CLK $end
$var wire 1 $ CLR $end
$var wire 4 2 D [4:1] $end
$var wire 2 3 G_bar [2:1] $end
$var wire 1 ) M $end
$var wire 1 ) N $end
$var wire 4 4 Q [4:1] $end
$var reg 4 5 Q_store [4:1] $end
$upscope $end
$upscope $end
$upscope $end
$enddefinitions $end
$comment Show the parameter values. $end
$dumpall
$end
#0
$dumpvars
bx 5
bx 4
b11 3
b1010 2
bx 1
bz 0
b11 /
b1100 .
b1100 -
b1010 ,
bz +
bx *
0)
b10101100 (
b10101100 '
1&
1%
0$
0#
bz "
bx !
$end
#1
b0 !
b0 *
b0 4
b0 5
1$
1#
#2
0$
0#
#3
b1010 !
b1010 *
b1010 4
b1100 1
b1010 5
b0 /
b0 3
0&
1#
#4
0#
#5
b1100 "
b1100 +
b1100 0
1#
0%
#6
0#
#7
b1101 "
b1101 +
b1101 0
b11 !
b11 *
b11 4
b1101 1
b11 5
b11 ,
b11 2
b1101 -
b1101 .
1#
b111101 '
b111101 (
#8
0#
#9
1#
b11 /
b11 3
1&
#10
0#
#11
b1111 ,
b1111 2
b1111 -
b1111 .
1#
b11111111 '
b11111111 (
#12
0#
#13
bz "
bz +
bz 0
1#
1%
#14
0#
#15
1#
#16
b0 !
b0 *
b0 4
b0 5
0#
1$
#17
1#
0$
