7400/SN74189/SN74189.v
module SN74189(A, DI, DO, S_bar, W_bar);
   input [3:0] A;
   input [3:0] DI;
   output [3:0] DO;
   input S_bar, W_bar;

   reg [3:0] mem[15:0]; reg [3:0] d_out;

   assign DO = (!S_bar && W_bar) ? ~d_out : 4'hz;
   // Write
   always @(A, DI, S_bar, W_bar)
     if (!S_bar && !W_bar) mem[A] = DI;
   // Read
   always @(A, S_bar, W_bar)
     if (!S_bar && W_bar) d_out = mem[A];
endmodule

module SN74189_tb;
   `ifdef SN74189_test
   reg [3:0] address;
   wire [3:0] data_out;
   reg [3:0] data_in;
   reg write_bar, select_bar;
   integer k, myseed;

   SN74189 DUT (address, data_in, data_out, select_bar, write_bar);

   initial
     begin
        $dumpfile("SN74189_tb.vcd");
        $dumpvars(0, SN74189_tb);
        for (k=0; k<=15; k=k+1)
          begin
             data_in = (k+5) % 16; address = k; write_bar = 0; select_bar = 0; #2;
          end
        repeat (20)
          begin
             address = $random(myseed) % 16;
             write_bar = 1; select_bar = 0;
             #2;
             $display ("Address : %2d, Data: %2d", address, ~data_out);
          end
        select_bar = 1;
        #5;
     end
   initial myseed = 314;
   `endif
endmodule

SAP-1/Architecture/RAM 16x8/RAM_16x8.v
`ifndef SN74189
   `define SN74189
   `include "7400/SN74189/SN74189.v"
`endif
module RAM_16x8(address, CE_bar, memory_value, run_or_prog, read_or_write, programmer_data);
   input [3:0] address;
   input CE_bar;
   output [7:0] memory_value;
   input run_or_prog;
   input read_or_write;
   input [7:0] programmer_data;

   wire [3:0] ram_output_first_nibble;
   wire [3:0] ram_output_second_nibble;
   assign memory_value = {ram_output_second_nibble, ram_output_first_nibble};

   wire gnd = 0;

   wire chip_select = run_or_prog ? CE_bar : gnd;

   SN74189 ram_1(.A(address), .DI(programmer_data[3:0]), .DO(ram_output_first_nibble),  .S_bar(chip_select), .W_bar(read_or_write));
   SN74189 ram_2(.A(address), .DI(programmer_data[7:4]), .DO(ram_output_second_nibble), .S_bar(chip_select), .W_bar(read_or_write));
endmodule

module RAM_16x8_tb;
   `ifdef RAM_16x8_test
   reg [3:0] address;
   reg CE_bar;
   wire [7:0] memory_value;
   reg run_or_prog;
   reg read_or_write;
   reg [7:0] programmer_data;
   integer k, myseed;

   RAM_16x8 DUT(address, CE_bar, memory_value, run_or_prog, read_or_write, programmer_data);

   initial begin
      // Waveform generation
      $dumpfile("RAM_16x8_tb.vcd");
      $dumpvars(0, RAM_16x8_tb);
      // Drive the bus when in run mode
      CE_bar = 0;
      // Write data into memory
      run_or_prog = 0;
      read_or_write = 0;
      for (k=0; k<=15; k=k+1)
        begin
           programmer_data = (k-3) % 16; address = k; #1;
        end
      // Read data from memory
      run_or_prog = 1;
      read_or_write = 1;
      #1;
      repeat (20)
        begin
           address = $random(myseed) % 16;
           #1;
           $display ("Address : %2d, Data: %2d", address, memory_value);
        end
      CE_bar = 1;
      #5;
   end
   initial myseed = 314;
   `endif
endmodule

SAP-1/Architecture/RAM 16x8/RAM_16x8_tb.vcd
$date
	Wed Dec 13 14:52:01 2023
$end
$version
	Icarus Verilog
$end
$timescale
	1s
$end
$scope module RAM_16x8_tb $end
$var wire 8 ! memory_value [7:0] $end
$var reg 1 " CE_bar $end
$var reg 4 # address [3:0] $end
$var reg 8 $ programmer_data [7:0] $end
$var reg 1 % read_or_write $end
$var reg 1 & run_or_prog $end
$var integer 32 ' k [31:0] $end
$var integer 32 ( myseed [31:0] $end
$scope module DUT $end
$var wire 1 " CE_bar $end
$var wire 4 ) address [3:0] $end
$var wire 1 * gnd $end
$var wire 8 + programmer_data [7:0] $end
$var wire 1 % read_or_write $end
$var wire 1 & run_or_prog $end
$var wire 4 , ram_output_second_nibble [3:0] $end
$var wire 4 - ram_output_first_nibble [3:0] $end
$var wire 8 . memory_value [7:0] $end
$var wire 1 / chip_select $end
$scope module ram_1 $end
$var wire 4 0 A [3:0] $end
$var wire 4 1 DI [3:0] $end
$var wire 1 / S_bar $end
$var wire 1 % W_bar $end
$var wire 4 2 DO [3:0] $end
$var reg 4 3 d_out [3:0] $end
$upscope $end
$scope module ram_2 $end
$var wire 4 4 A [3:0] $end
$var wire 4 5 DI [3:0] $end
$var wire 1 / S_bar $end
$var wire 1 % W_bar $end
$var wire 4 6 DO [3:0] $end
$var reg 4 7 d_out [3:0] $end
$upscope $end
$upscope $end
$upscope $end
$enddefinitions $end
$comment Show the parameter values. $end
$dumpall
$end
#0
$dumpvars
bx 7
bz 6
b1111 5
b0 4
bx 3
bz 2
b1101 1
b0 0
0/
bx .
bz -
bz ,
b11111101 +
0*
b0 )
b100111010 (
b0 '
0&
0%
b11111101 $
b0 #
0"
bx !
$end
#1
b1110 1
b1 #
b1 )
b1 0
b1 4
b11111110 $
b11111110 +
b1 '
#2
b1111 1
b10 #
b10 )
b10 0
b10 4
b11111111 $
b11111111 +
b10 '
#3
b0 1
b0 5
b11 #
b11 )
b11 0
b11 4
b0 $
b0 +
b11 '
#4
b1 1
b100 #
b100 )
b100 0
b100 4
b1 $
b1 +
b100 '
#5
b10 1
b101 #
b101 )
b101 0
b101 4
b10 $
b10 +
b101 '
#6
b11 1
b110 #
b110 )
b110 0
b110 4
b11 $
b11 +
b110 '
#7
b100 1
b111 #
b111 )
b111 0
b111 4
b100 $
b100 +
b111 '
#8
b101 1
b1000 #
b1000 )
b1000 0
b1000 4
b101 $
b101 +
b1000 '
#9
b110 1
b1001 #
b1001 )
b1001 0
b1001 4
b110 $
b110 +
b1001 '
#10
b111 1
b1010 #
b1010 )
b1010 0
b1010 4
b111 $
b111 +
b1010 '
#11
b1000 1
b1011 #
b1011 )
b1011 0
b1011 4
b1000 $
b1000 +
b1011 '
#12
b1001 1
b1100 #
b1100 )
b1100 0
b1100 4
b1001 $
b1001 +
b1100 '
#13
b1010 1
b1101 #
b1101 )
b1101 0
b1101 4
b1010 $
b1010 +
b1101 '
#14
b1011 1
b1110 #
b1110 )
b1110 0
b1110 4
b1011 $
b1011 +
b1110 '
#15
b1100 1
b1111 #
b1111 )
b1111 0
b1111 4
b1100 $
b1100 +
b1111 '
#16
b1100 !
b1100 .
b11 -
b11 2
b1111 ,
b1111 6
b0 7
b1100 3
1%
1&
b10000 '
#17
b11111111 !
b11111111 .
b0 -
b0 2
b0 ,
b0 6
b1111 3
b1111 7
b10 #
b10 )
b10 0
b10 4
b1010010101110110101110011 (
#18
b110 !
b110 .
b1111 ,
b1111 6
b1001 -
b1001 2
b0 7
b110 3
b1001 #
b1001 )
b1001 0
b1001 4
b11000100100000011111110000011000 (
#19
b0 !
b0 .
b1111 -
b1111 2
b0 3
b11 #
b11 )
b11 0
b11 4
b11110001111111000001011100111001 (
#20
b11 !
b11 .
b1100 -
b1100 2
b11 3
b110 #
b110 )
b110 0
b110 4
b10101011010001010111110110100110 (
#21
b100 !
b100 .
b1011 -
b1011 2
b100 3
b111 #
b111 )
b111 0
b111 4
b101011101011010000101111101111 (
#22
b1011 !
b1011 .
b100 -
b100 2
b1011 3
b1110 #
b1110 )
b1110 0
b1110 4
b11001111000111001011000101100100 (
#23
b11111101 !
b11111101 .
b10 -
b10 2
b0 ,
b0 6
b1101 3
b1111 7
b0 #
b0 )
b0 0
b0 4
b11000000010000100010101 (
#24
b1100 !
b1100 .
b1111 ,
b1111 6
b11 -
b11 2
b0 7
b1100 3
b1111 #
b1111 )
b1111 0
b1111 4
b1001111101111011000111011010010 (
#25
b0 !
b0 .
b1111 -
b1111 2
b0 3
b11 #
b11 )
b11 0
b11 4
b1001110111100000100000101011 (
#26
b111 !
b111 .
b1000 -
b1000 2
b111 3
b1010 #
b1010 )
b1010 0
b1010 4
b110101011000011011100101110000 (
#27
b1011 !
b1011 .
b100 -
b100 2
b1011 3
b1110 #
b1110 )
b1110 0
b1110 4
b1101111000111000010111010110001 (
#28
b1010 !
b1010 .
b101 -
b101 2
b1010 3
b1101 #
b1101 )
b1101 0
b1101 4
b10010110101000010110000010111110 (
#29
b0 !
b0 .
b1111 -
b1111 2
b0 3
b11 #
b11 )
b11 0
b11 4
b110001111000100001111000100111 (
#30
b100 !
b100 .
b1011 -
b1011 2
b100 3
b111 #
b111 )
b111 0
b111 4
b10001011110000010010000000111100 (
#31
b11111110 !
b11111110 .
b1 -
b1 2
b0 ,
b0 6
b1110 3
b1111 7
b1 #
b1 )
b1 0
b1 4
b11011000100001011101110000001101 (
#32
b11 !
b11 .
b1111 ,
b1111 6
b1100 -
b1100 2
b0 7
b11 3
b110 #
b110 )
b110 0
b110 4
b1011011010101101111101101010 (
#33
b11111111 !
b11111111 .
b0 -
b0 2
b0 ,
b0 6
b1111 3
b1111 7
b10 #
b10 )
b10 0
b10 4
b1110001010101110100100111100011 (
#34
b100 !
b100 .
b1111 ,
b1111 6
b1011 -
b1011 2
b0 7
b100 3
b111 #
b111 )
b111 0
b111 4
b1111011100010011011000111001000 (
#35
b111 !
b111 .
b1000 -
b1000 2
b111 3
b1010 #
b1010 )
b1010 0
b1010 4
b10011101000100101000010100101001 (
#36
b1000 !
b1000 .
b111 -
b111 2
b1000 3
b1011 #
b1011 )
b1011 0
b1011 4
b111101110000001011011011010110 (
#37
bz -
bz 2
bz ,
bz 6
bz !
bz .
1/
1"
