7400/SN74LS126/SN74LS126.v
module SN74LS126(A, G, Y);
   input [4:1] A;
   input [4:1] G;
   output [4:1] Y;


   assign Y[1] = G[1] ? A[1] : 1'bZ;
   assign Y[2] = G[2] ? A[2] : 1'bZ;
   assign Y[3] = G[3] ? A[3] : 1'bZ;
   assign Y[4] = G[4] ? A[4] : 1'bZ;
endmodule

module SN74LS126_tb;
   `ifdef SN74LS126_test
   reg [4:1] a;
   reg [4:1] g;
   wire [4:1] y;

   SN74LS126 UUT (
        .A1(a[1]), .G1(g[1]), .Y1(y[1]),
        .A2(a[2]), .G2(g[2]), .Y2(y[2]),
        .A3(a[3]), .G3(g[3]), .Y3(y[3]),
        .A4(a[4]), .G4(g[4]), .Y4(y[4])
        );
   initial begin
        // Waveform generation
        $dumpfile("SN74LS126_tb.vcd");
        $dumpvars(0, SN74LS126_tb);

        a = 0;
        g = 0;
        for (int i=0; i<4; i=i+1) begin
            {g[1], a[1]} = i; #5;
        end
        for (int i=0; i<4; i=i+1) begin
            {g[2], a[2]} = i; #5;
        end
        for (int i=0; i<4; i=i+1) begin
            {g[3], a[3]} = i; #5;
        end
        for (int i=0; i<4; i=i+1) begin
            {g[4], a[4]} = i; #5;
        end
   end
   `endif
endmodule

7400/SN74LS107/SN74LS107.v
module JK_FlipFlop(CLR_bar, CLK, J, K, Q, Q_bar);
   input CLR_bar;
   input CLK;
   input J;
   input K;
   output reg Q, Q_bar;

   always @(posedge CLK or posedge CLR_bar) begin
      if (~CLR_bar) begin
         Q <= 0;
         Q_bar <= 1;
      end
      else begin
         Q <= (J & Q_bar) | (~K & Q);
         Q_bar <= ~((J & Q_bar) | (~K & Q));
      end
   end
endmodule
module SN74LS107(CLK_1, CLR_bar_1, J_1, K_1, Q_1, Q_bar_1, CLK_2, CLR_bar_2, J_2, K_2, Q_2, Q_bar_2);
   input CLK_1, CLK_2;
   input CLR_bar_1, CLR_bar_2;
   input J_1, J_2;
   input K_1, K_2;
   output Q_1, Q_bar_1, Q_2, Q_bar_2;

   JK_FlipFlop FF_1(.CLR_bar(CLR_bar_1), .CLK(CLK_1), .J(J_1), .K(K_1), .Q(Q_1), .Q_bar(Q_bar_1));
   JK_FlipFlop FF_2(.CLR_bar(CLR_bar_2), .CLK(CLK_2), .J(J_2), .K(K_2), .Q(Q_2), .Q_bar(Q_bar_2));
endmodule

module SN74LS107_tb;
   `ifdef SN74LS107_test
   reg CLK;
   reg CLR_bar_1, J_1, K_1;
   wire Q_1, Q_bar_1;
   reg CLR_bar_2, J_2, K_2;
   wire Q_2, Q_bar_2;


   SN74LS107 DUT(.CLK_1(CLK), .CLR_bar_1(CLR_bar_1), .J_1(J_1), .K_1(K_1), .Q_1(Q_1), .Q_bar_1(Q_bar_1),
                 .CLK_2(CLK), .CLR_bar_2(CLR_bar_2), .J_2(J_2), .K_2(K_2), .Q_2(Q_2), .Q_bar_2(Q_bar_2));
   initial begin
      CLK=0;
      forever #1 CLK = ~CLK;
   end
   initial begin
      // Waveform generation
      $dumpfile("SN74LS107_tb.vcd");
      $dumpvars(0, SN74LS107_tb);
      CLR_bar_1 = 0; CLR_bar_2 = 0;
      #2;
      CLR_bar_1 = 1;
      // Test flip-flop 1
      J_1 = 0; K_1 = 1; // Set Q = 0
      #2;
      J_1 = 0; K_1 = 0; // Hold value
      #2;
      J_1 = 1; K_1 = 0; // Set Q = 1
      #2;
      J_1 = 0; K_1 = 0; // Hold value
      #2;
      J_1 = 1; K_1 = 1; // Toggle value
      #2
      // Test flip-flop 2
      CLR_bar_2 = 1;
      J_2 = 1; K_2 = 0; // Set Q = 1
      #2;
      J_2 = 0; K_2 = 0; // Hold value
      #2;
      J_2 = 0; K_2 = 1; // Set Q = 0
      #2;
      J_2 = 0; K_2 = 0; // Hold value
      #2;
      J_2 = 1; K_2 = 1; // Toggle value
      #2
      $finish;
   end
   `endif
endmodule

SAP-1/Architecture/Program Counter/Program_Counter.v
`include "../../../7400/SN74LS107/SN74LS107.v"
`include "../../../7400/SN74LS126/SN74LS126.v"
module Program_Counter(C_P, CLK_bar, CLR_bar, E_P, address);
    input C_P;
    input CLK_bar;
    input CLR_bar;
    input E_P;
    output [3:0] address;

   wire [3:0] Q;
   SN74LS107 dualFF_1(.CLK_1(!CLK_bar), .CLR_bar_1(CLR_bar), .J_1(C_P), .K_1(C_P), .Q_1(Q[0]),
                      .CLK_2(!Q[0]), .CLR_bar_2(CLR_bar), .J_2(C_P), .K_2(C_P), .Q_2(Q[1]));
   SN74LS107 dualFF_2(.CLK_1(!Q[1]), .CLR_bar_1(CLR_bar), .J_1(C_P), .K_1(C_P), .Q_1(Q[2]),
                      .CLK_2(!Q[2]), .CLR_bar_2(CLR_bar), .J_2(C_P), .K_2(C_P), .Q_2(Q[3]));
   SN74LS126 tristateBuffer(.A(Q), .G({4{E_P}}), .Y(address));

endmodule

module Program_Counter_tb;
   `ifdef Program_Counter_test
   reg C_P;
   reg CLK_bar;
   reg CLR_bar;
   reg E_P;
   wire [3:0] address;

   Program_Counter DUT(C_P, CLK_bar, CLR_bar, E_P, address);
   initial begin
      CLK_bar = 1;
      forever #1 CLK_bar = ~CLK_bar;
   end
   initial begin
      // Waveform generation
      $dumpfile("Program_Counter_tb.vcd");
      $dumpvars(0, Program_Counter_tb);
      CLR_bar = 1;
      // Disable counting
      C_P = 0;
      // Enable output
      E_P = 1;
      // Clear the value
      #1;
      CLR_bar = 0;
      #1;
      CLR_bar = 1;
      #1;
      // Enable counting
      C_P = 1;
      #20;
      // Disable counting
      C_P = 0;
      #4;
      // Disable output
      E_P = 0;
      #4;
      $finish;
   end
   `endif
endmodule

SAP-1/Architecture/Program Counter/Program_Counter_tb.vcd
$date
	Sat Dec  9 10:27:05 2023
$end
$version
	Icarus Verilog
$end
$timescale
	1s
$end
$scope module Program_Counter_tb $end
$var wire 4 ! address [3:0] $end
$var reg 1 " CLK_bar $end
$var reg 1 # CLR_bar $end
$var reg 1 $ C_P $end
$var reg 1 % E_P $end
$scope module DUT $end
$var wire 1 " CLK_bar $end
$var wire 1 # CLR_bar $end
$var wire 1 $ C_P $end
$var wire 1 % E_P $end
$var wire 4 & address [3:0] $end
$var wire 4 ' Q [3:0] $end
$scope module dualFF_1 $end
$var wire 1 ( CLK_1 $end
$var wire 1 ) CLK_2 $end
$var wire 1 # CLR_bar_1 $end
$var wire 1 # CLR_bar_2 $end
$var wire 1 $ J_1 $end
$var wire 1 $ J_2 $end
$var wire 1 $ K_1 $end
$var wire 1 $ K_2 $end
$var wire 1 * Q_bar_2 $end
$var wire 1 + Q_bar_1 $end
$var wire 1 , Q_2 $end
$var wire 1 - Q_1 $end
$scope module FF_1 $end
$var wire 1 ( CLK $end
$var wire 1 # CLR_bar $end
$var wire 1 $ J $end
$var wire 1 $ K $end
$var reg 1 - Q $end
$var reg 1 + Q_bar $end
$upscope $end
$scope module FF_2 $end
$var wire 1 ) CLK $end
$var wire 1 # CLR_bar $end
$var wire 1 $ J $end
$var wire 1 $ K $end
$var reg 1 , Q $end
$var reg 1 * Q_bar $end
$upscope $end
$upscope $end
$scope module dualFF_2 $end
$var wire 1 . CLK_1 $end
$var wire 1 / CLK_2 $end
$var wire 1 # CLR_bar_1 $end
$var wire 1 # CLR_bar_2 $end
$var wire 1 $ J_1 $end
$var wire 1 $ J_2 $end
$var wire 1 $ K_1 $end
$var wire 1 $ K_2 $end
$var wire 1 0 Q_bar_2 $end
$var wire 1 1 Q_bar_1 $end
$var wire 1 2 Q_2 $end
$var wire 1 3 Q_1 $end
$scope module FF_1 $end
$var wire 1 . CLK $end
$var wire 1 # CLR_bar $end
$var wire 1 $ J $end
$var wire 1 $ K $end
$var reg 1 3 Q $end
$var reg 1 1 Q_bar $end
$upscope $end
$scope module FF_2 $end
$var wire 1 / CLK $end
$var wire 1 # CLR_bar $end
$var wire 1 $ J $end
$var wire 1 $ K $end
$var reg 1 2 Q $end
$var reg 1 0 Q_bar $end
$upscope $end
$upscope $end
$scope module tristateBuffer $end
$var wire 4 4 A [4:1] $end
$var wire 4 5 G [4:1] $end
$var wire 4 6 Y [4:1] $end
$upscope $end
$upscope $end
$upscope $end
$enddefinitions $end
$comment Show the parameter values. $end
$dumpall
$end
#0
$dumpvars
bx 6
b1111 5
bx 4
x3
x2
x1
x0
x/
x.
x-
x,
x+
x*
x)
0(
bx '
bx &
1%
0$
1#
1"
bx !
$end
#1
10
02
1/
11
03
1.
1*
0,
b0 !
b0 &
b0 6
1)
1+
b0 '
b0 4
0-
0#
1(
0"
#2
1#
0(
1"
#3
b1 !
b1 &
b1 6
0)
0+
b1 '
b1 4
1-
1$
1(
0"
#4
0(
1"
#5
0.
0*
1,
b10 !
b10 &
b10 6
1)
1+
b10 '
b10 4
0-
1(
0"
#6
0(
1"
#7
b11 !
b11 &
b11 6
0)
0+
b11 '
b11 4
1-
1(
0"
#8
0(
1"
#9
0/
01
13
1.
1*
0,
b100 !
b100 &
b100 6
1)
1+
b100 '
b100 4
0-
1(
0"
#10
0(
1"
#11
b101 !
b101 &
b101 6
0)
0+
b101 '
b101 4
1-
1(
0"
#12
0(
1"
#13
0.
0*
1,
b110 !
b110 &
b110 6
1)
1+
b110 '
b110 4
0-
1(
0"
#14
0(
1"
#15
b111 !
b111 &
b111 6
0)
0+
b111 '
b111 4
1-
1(
0"
#16
0(
1"
#17
00
12
1/
11
03
1.
1*
0,
b1000 !
b1000 &
b1000 6
1)
1+
b1000 '
b1000 4
0-
1(
0"
#18
0(
1"
#19
b1001 !
b1001 &
b1001 6
0)
0+
b1001 '
b1001 4
1-
1(
0"
#20
0(
1"
#21
0.
0*
1,
b1010 !
b1010 &
b1010 6
1)
1+
b1010 '
b1010 4
0-
1(
0"
#22
0(
1"
#23
1(
0"
0$
#24
0(
1"
#25
1(
0"
#26
0(
1"
#27
bz !
bz &
bz 6
1(
0"
b0 5
0%
