7400/SN74LS83/SN74LS83.v
module SN74LS83(A, B, C0, C4, S);
   input [3:0] A;
   input [3:0] B;
   input C0;
   output C4;
   output [3:0] S;

   assign {C4, S} = A + B + C0;
endmodule

module SN74LS83_tb;
   reg [3:0] a;
   reg [3:0] b;
   reg carry_in;
   wire carry_out;
   wire [3:0] sum;
   integer myseed;

   SN74LS83 DUT(a, b, carry_in, carry_out, sum);

   initial
     begin
        $dumpfile("SN74LS83.vcd");
        $dumpvars(0, SN74LS83_tb);
        repeat (20)
          begin
             a = $random(myseed) % 16;
             b = $random(myseed) % 16;
             carry_in = $random(myseed) % 2;
             #2;
             $display ("%2d + %2d + %2d = %2d, Carry = %2d", a, b, carry_in, sum+16*carry_out, carry_out);
          end
     end
   initial myseed = 314;
endmodule

7400/SN74LS83/SN74LS83.vcd
$date
	Wed Dec  6 12:05:49 2023
$end
$version
	Icarus Verilog
$end
$timescale
	1s
$end
$scope module SN74LS83_tb $end
$var wire 4 ! sum [3:0] $end
$var wire 1 " carry_out $end
$var reg 4 # a [3:0] $end
$var reg 4 $ b [3:0] $end
$var reg 1 % carry_in $end
$var integer 32 & myseed [31:0] $end
$scope module DUT $end
$var wire 4 ' A [3:0] $end
$var wire 4 ( B [3:0] $end
$var wire 1 % C0 $end
$var wire 4 ) S [3:0] $end
$var wire 1 " C4 $end
$upscope $end
$upscope $end
$enddefinitions $end
$comment Show the parameter values. $end
$dumpall
$end
#0
$dumpvars
b110 )
b1 (
b100 '
b100111010 &
1%
b1 $
b100 #
0"
b110 !
$end
#2
b1100 !
b1100 )
b1001 $
b1001 (
b10 #
b10 '
b11110001111111000001011100111001 &
#4
b1101 !
b1101 )
0%
b111 $
b111 (
b110 #
b110 '
b11001111000111001011000101100100 &
#6
1"
b0 !
b0 )
1%
b1111 $
b1111 (
b0 #
b0 '
b1001110111100000100000101011 &
#8
b1001 !
b1001 )
b1110 $
b1110 (
b1010 #
b1010 '
b10010110101000010110000010111110 &
#10
0"
b1011 !
b1011 )
b111 $
b111 (
b11 #
b11 '
b11011000100001011101110000001101 &
#12
b1001 !
b1001 )
b10 $
b10 (
b110 #
b110 '
b1111011100010011011000111001000 &
#14
1"
b101 !
b101 )
0%
b1011 $
b1011 (
b1010 #
b1010 '
b11110011011100010100011101011111 &
#16
b100 !
b100 )
0"
b1 $
b1 (
b11 #
b11 '
b10010000001000100101001100000010 &
#18
b1010 !
b1010 )
1%
b0 $
b0 (
b1001 #
b1001 '
b11111100001111101010100001 &
#20
b1110 !
b1110 )
0%
b1110 #
b1110 '
b11101111011101111001111011101100 &
#22
1"
b110 !
b110 )
b1101 $
b1101 (
b1001 #
b1001 '
b1010100000100111100001001010011 &
#24
b100 !
b100 )
b110 $
b110 (
b1110 #
b1110 '
b1000100010101110011110000000110 &
#26
b1011 !
b1011 )
0"
1%
b11 $
b11 (
b111 #
b111 '
b10100101111000001010011011110101 &
#28
1"
b100 !
b100 )
0%
b1100 $
b1100 (
b1000 #
b1000 '
b1100001000011001011110011010000 &
#30
b110 !
b110 )
0"
b11 $
b11 (
b11 #
b11 '
b10110111001010000000110100000111 &
#32
b101 !
b101 )
1%
b1 #
b1 '
b101110000010011111111001010 &
#34
1"
b1 !
b1 )
b1001 $
b1001 (
b111 #
b111 '
b10001011111100111101010100001001 &
#36
b1100 !
b1100 )
0"
0%
b1010 $
b1010 (
b10 #
b10 '
b10110001001100000111101110100 &
#38
1"
b11 !
b11 )
b1110 $
b1110 (
b101 #
b101 '
b11000011010111100111101101111011 &
