7400/SN74189/SN74189.v
module SN74189(A, DI, DO, S_bar, W_bar);
   input [3:0] A;
   input [3:0] DI;
   output [3:0] DO;
   input S_bar, W_bar;

   reg [3:0] mem[15:0]; reg [3:0] d_out;

   assign DO = (!S_bar && W_bar) ? ~d_out : 4'hz;
   // Write
   always @(A, DI, S_bar, W_bar)
     if (!S_bar && !W_bar) mem[A] = DI;
   // Read
   always @(A, S_bar, W_bar)
     if (!S_bar && W_bar) d_out = mem[A];
endmodule

module SN74189_tb;
   reg [3:0] address;
   wire [3:0] data_out;
   reg [3:0] data_in;
   reg write_bar, select_bar;
   integer k, myseed;

   SN74189 DUT (address, data_in, data_out, select_bar, write_bar);

   initial
     begin
        $dumpfile("SN74189_tb.vcd");
        $dumpvars(0, SN74189_tb);
        for (k=0; k<=15; k=k+1)
          begin
             data_in = (k+5) % 16; address = k; write_bar = 0; select_bar = 0; #2;
          end
        repeat (20)
          begin
             address = $random(myseed) % 16;
             write_bar = 1; select_bar = 0;
             #2;
             $display ("Address : %2d, Data: %2d", address, ~data_out);
          end
     end
   initial myseed = 314;
endmodule

7400/SN74189/SN74189_tb.vcd
$date
	Tue Dec  5 23:33:44 2023
$end
$version
	Icarus Verilog
$end
$timescale
	1s
$end
$scope module SN74189_tb $end
$var wire 4 ! data_out [3:0] $end
$var reg 4 " address [3:0] $end
$var reg 4 # data_in [3:0] $end
$var reg 1 $ select_bar $end
$var reg 1 % write_bar $end
$var integer 32 & k [31:0] $end
$var integer 32 ' myseed [31:0] $end
$scope module DUT $end
$var wire 4 ( A [3:0] $end
$var wire 4 ) DI [3:0] $end
$var wire 1 $ S_bar $end
$var wire 1 % W_bar $end
$var wire 4 * DO [3:0] $end
$var reg 4 + d_out [3:0] $end
$upscope $end
$upscope $end
$enddefinitions $end
$comment Show the parameter values. $end
$dumpall
$end
#0
$dumpvars
bx +
bz *
b101 )
b0 (
b100111010 '
b0 &
0%
0$
b101 #
b0 "
bz !
$end
#2
b1 "
b1 (
b110 #
b110 )
b1 &
#4
b10 "
b10 (
b111 #
b111 )
b10 &
#6
b11 "
b11 (
b1000 #
b1000 )
b11 &
#8
b100 "
b100 (
b1001 #
b1001 )
b100 &
#10
b101 "
b101 (
b1010 #
b1010 )
b101 &
#12
b110 "
b110 (
b1011 #
b1011 )
b110 &
#14
b111 "
b111 (
b1100 #
b1100 )
b111 &
#16
b1000 "
b1000 (
b1101 #
b1101 )
b1000 &
#18
b1001 "
b1001 (
b1110 #
b1110 )
b1001 &
#20
b1010 "
b1010 (
b1111 #
b1111 )
b1010 &
#22
b1011 "
b1011 (
b0 #
b0 )
b1011 &
#24
b1100 "
b1100 (
b1 #
b1 )
b1100 &
#26
b1101 "
b1101 (
b10 #
b10 )
b1101 &
#28
b1110 "
b1110 (
b11 #
b11 )
b1110 &
#30
b1111 "
b1111 (
b100 #
b100 )
b1111 &
#32
b1000 !
b1000 *
b111 +
1%
b10 "
b10 (
b1010010101110110101110011 '
b10000 &
#34
b1 !
b1 *
b1110 +
b1001 "
b1001 (
b11000100100000011111110000011000 '
#36
b111 !
b111 *
b1000 +
b11 "
b11 (
b11110001111111000001011100111001 '
#38
b100 !
b100 *
b1011 +
b110 "
b110 (
b10101011010001010111110110100110 '
#40
b11 !
b11 *
b1100 +
b111 "
b111 (
b101011101011010000101111101111 '
#42
b1100 !
b1100 *
b11 +
b1110 "
b1110 (
b11001111000111001011000101100100 '
#44
b1010 !
b1010 *
b101 +
b0 "
b0 (
b11000000010000100010101 '
#46
b1011 !
b1011 *
b100 +
b1111 "
b1111 (
b1001111101111011000111011010010 '
#48
b111 !
b111 *
b1000 +
b11 "
b11 (
b1001110111100000100000101011 '
#50
b0 !
b0 *
b1111 +
b1010 "
b1010 (
b110101011000011011100101110000 '
#52
b1100 !
b1100 *
b11 +
b1110 "
b1110 (
b1101111000111000010111010110001 '
#54
b1101 !
b1101 *
b10 +
b1101 "
b1101 (
b10010110101000010110000010111110 '
#56
b111 !
b111 *
b1000 +
b11 "
b11 (
b110001111000100001111000100111 '
#58
b11 !
b11 *
b1100 +
b111 "
b111 (
b10001011110000010010000000111100 '
#60
b1001 !
b1001 *
b110 +
b1 "
b1 (
b11011000100001011101110000001101 '
#62
b100 !
b100 *
b1011 +
b110 "
b110 (
b1011011010101101111101101010 '
#64
b1000 !
b1000 *
b111 +
b10 "
b10 (
b1110001010101110100100111100011 '
#66
b11 !
b11 *
b1100 +
b111 "
b111 (
b1111011100010011011000111001000 '
#68
b0 !
b0 *
b1111 +
b1010 "
b1010 (
b10011101000100101000010100101001 '
#70
b1111 !
b1111 *
b0 +
b1011 "
b1011 (
b111101110000001011011011010110 '
