7400/SN74LS173/SN74LS173.v
module SN74LS173(D, Q, CLK, CLR, G_bar, M, N);
   input [4:1] D;
   output reg [4:1] Q;
   input [2:1] G_bar;
   input CLK, CLR, M, N;

   reg [4:1] Q_store;

   assign Q = (M | N) ? 4'hz : Q_store;

   always @(posedge CLK, CLR) begin
      if (CLR)
        Q_store <= 0;
      else
        if (!G_bar[1] && !G_bar[2])
          Q_store <= D;
   end
endmodule

module SN74LS173_tb;
   `ifdef SN74LS173_test
   reg [4:1] d;
   reg CLK;
   reg CLR;
   wire [4:1] q;
   reg m, n;
   reg [2:1] g_bar;
   SN74LS173 DUT(.D(d), .Q(q), .CLK(CLK), .CLR(CLR), .G_bar(g_bar), .M(m), .N(n));

   initial begin
      // Waveform generation
      $dumpfile("SN74LS173_tb.vcd");
      $dumpvars(0, SN74LS173_tb);
      $display("------------------");
      $display("Set Output to Q");
      m = 0;
      n = 0;
      $display("Enable Data Writing");
      g_bar = 2'b00;
      d = 4'h9;
      $display("Set Data to %h", d);
      CLK=0;
      $display("Enable Clear");
      CLR = 1;
      forever #1 CLK = ~CLK;
   end
   initial begin
      #1
      $display("Disable Clear");
      CLR = 0;
      #1;
      d = 4'h3;
      $display("Set Data to %h", d);
      #1
      $display("Set Output to High Impedence");
      m = 1;
      n = 1;
      #1;
      d = 4'hC;
      $display("Set Data to %h", d);
      #1
      $display("Set Output to Q");
      m = 0;
      n = 0;
      #1;
      $display("Disable Data Writing");
      g_bar = 2'b11;
      #1;
      d = 4'hF;
      $display("Set Data to %h", d);
      #1
      $display("------------------");
      $finish;
   end
   `endif
endmodule

7400/SN74LS157/SN74LS157.v
module SN74LS157(A, B, Y, G_bar, SELECT);
   input G_bar, SELECT;
   input [4:1] A, B;
   output reg [4:1] Y;

   always @(*) begin
      if (G_bar) begin
          Y = 0;
      end else begin
          if (SELECT) begin
              Y = B;
          end else begin
              Y = A;
          end
      end
   end
endmodule

module SN74LS157_tb;
   `ifdef SN74LS157_test
   reg g_bar;
   reg select;
   reg [4:1] a, b;
   wire [4:1] y;


   SN74LS157 DUT(.G_bar(g_bar), .SELECT(select), .A(a), .B(b), .Y(y));

   initial begin
      // Waveform generation
      $dumpfile("SN74LS157_tb.vcd");
      $dumpvars(0, SN74LS157_tb);

      // Force output to 0
      g_bar = 1;
      // Select input a
      select = 0;
      // Set initial values
      a = 3;
      b = 7;
      #1;
      // Stop forcing output to 0
      g_bar = 0;
      #1;
      // Select input b
      select = 1;
      #1
      // Force output to 0
      g_bar = 1;
      #1;
      // Change input a
      b = 4'hf;
      #1;
      // Stop forcing output to 0
      g_bar = 0;
      #1;
      // Select input a
      select = 0;
      #1
      $finish;
   end
   `endif
endmodule

SAP-1/Architecture/Input and MAR/SN74LS157_tb.vcd
$date
	Fri Dec  8 10:06:45 2023
$end
$version
	Icarus Verilog
$end
$timescale
	1s
$end
$scope module SN74LS157_tb $end
$var wire 4 ! y [4:1] $end
$var reg 4 " a [4:1] $end
$var reg 4 # b [4:1] $end
$var reg 1 $ g_bar $end
$var reg 1 % select $end
$scope module DUT $end
$var wire 4 & A [4:1] $end
$var wire 4 ' B [4:1] $end
$var wire 1 $ G_bar $end
$var wire 1 % SELECT $end
$var reg 4 ( Y [4:1] $end
$upscope $end
$upscope $end
$scope module SN74LS173_tb $end
$var wire 4 ) q [4:1] $end
$var reg 1 * CLK $end
$var reg 1 + CLR $end
$var reg 4 , d [4:1] $end
$var reg 2 - g_bar [2:1] $end
$var reg 1 . m $end
$var reg 1 / n $end
$scope module DUT $end
$var wire 1 * CLK $end
$var wire 1 + CLR $end
$var wire 4 0 D [4:1] $end
$var wire 2 1 G_bar [2:1] $end
$var wire 1 . M $end
$var wire 1 / N $end
$var wire 4 2 Q [4:1] $end
$var reg 4 3 Q_store [4:1] $end
$upscope $end
$upscope $end
$enddefinitions $end
$comment Show the parameter values. $end
$dumpall
$end
#0
$dumpvars
b0 3
b0 2
b0 1
b1001 0
0/
0.
b0 -
b1001 ,
1+
0*
b0 )
b0 (
b111 '
b11 &
0%
1$
b111 #
b11 "
b0 !
$end
#1
b1001 )
b1001 2
b1001 3
b11 !
b11 (
0+
1*
0$
#2
b111 !
b111 (
b11 ,
b11 0
0*
1%
#3
b11 3
bz )
bz 2
b0 !
b0 (
1/
1.
1*
1$
#4
b1100 ,
b1100 0
0*
b1111 #
b1111 '
#5
b1100 3
b1100 )
b1100 2
b1111 !
b1111 (
0/
0.
1*
0$
#6
b11 !
b11 (
b11 -
b11 1
0*
0%
#7
b1111 ,
b1111 0
1*
